jhu_primitives/__init__.py
jhu_primitives/sperf.py
jhu_primitives/ase/__init__.py
jhu_primitives/ase/ase.py
jhu_primitives/asgm_nomination/__init__.py
jhu_primitives/asgm_nomination/asgm_nomination.py
jhu_primitives/asgm_nomination/ali_sgm/__init__.py
jhu_primitives/asgm_nomination/ali_sgm/gmp.py
jhu_primitives/asgm_nomination/ali_sgm/qap.py
jhu_primitives/euclidean_nomination/__init__.py
jhu_primitives/euclidean_nomination/euclidean_nomination.py
jhu_primitives/gclass/__init__.py
jhu_primitives/gclass/gclass.py
jhu_primitives/gclust/__init__.py
jhu_primitives/gclust/gclust.py
jhu_primitives/lcc/__init__.py
jhu_primitives/lcc/lcc.py
jhu_primitives/link_pred_graph_reader/__init__.py
jhu_primitives/link_pred_graph_reader/link_pred_graph_reader.py
jhu_primitives/link_pred_rc/__init__.py
jhu_primitives/link_pred_rc/link_pred_rc.py
jhu_primitives/load_graphs/__init__.py
jhu_primitives/load_graphs/load_graphs.py
jhu_primitives/lse/__init__.py
jhu_primitives/lse/lse.py
jhu_primitives/nearest_neighbor_nomination/__init__.py
jhu_primitives/nearest_neighbor_nomination/nearest_neighbor_nomination.py
jhu_primitives/partial_procrustes/__init__.py
jhu_primitives/partial_procrustes/partial_procrustes.py
jhu_primitives/sgc/__init__.py
jhu_primitives/sgc/sgc.py
jhu_primitives/sgm/__init__.py
jhu_primitives/sgm/sgm.py
jhu_primitives/sgm/ben_sgm/__init__.py
jhu_primitives/sgm/ben_sgm/common.py
jhu_primitives/sgm/ben_sgm/lap_solvers.py
jhu_primitives/sgm/ben_sgm/utils.py
jhu_primitives/sgm/ben_sgm/backends/__init__.py
jhu_primitives/sgm/ben_sgm/backends/classic.py
jhu_primitives/sgm/ben_sgm/backends/fused.py
jhu_primitives/sgm/ben_sgm/backends/sparse.py
jhu_primitives/sgm_nomination/__init__.py
jhu_primitives/sgm_nomination/sgm_nomination.py
jhu_primitives/sgvn/__init__.py
jhu_primitives/sgvn/sgvn.py
jhu_primitives/utils/__init__.py
jhu_primitives/utils/util.py
jhu_primitives/utils/util_test.py
d3m_jhu_primitives-2022.7.8.dist-info/LICENSE
d3m_jhu_primitives-2022.7.8.dist-info/METADATA
d3m_jhu_primitives-2022.7.8.dist-info/WHEEL
d3m_jhu_primitives-2022.7.8.dist-info/entry_points.txt
d3m_jhu_primitives-2022.7.8.dist-info/top_level.txt
d3m_jhu_primitives-2022.7.8.dist-info/RECORD
