Metadata-Version: 2.1
Name: d3m-jhu-primitives
Version: 2022.7.8
Summary: JHU Python interfaces for TA1 primitives for d3m
Home-page: https://gitlab.com/datadrivendiscovery/contrib/jhu-primitives
Author: Hayden S. Helm, Joshua Agterberg, Bijan Varjavand, Anton Alyakin, Disa Mhembere, Eric Bridgeford, Youngser Park, Heather G. Patsolic, Tyler M. Tomita, Jesse L. Patsolic
Author-email: hhelm2@jhu.edu
License: Apache-2.0
Keywords: d3m_primitive
Platform: UNKNOWN
Requires-Dist: cython
Requires-Dist: d3m
Requires-Dist: graspy (==0.3.0)
Requires-Dist: hyppo (==0.1.3)
Requires-Dist: jinja2
Requires-Dist: lapjv (==1.3.14)
Requires-Dist: networkx
Requires-Dist: numba (>=0.52.0)
Requires-Dist: numpy
Requires-Dist: scipy
Requires-Dist: typing
